{
  "tabPane": [
    {
      "title": "Teleop",
      "autoPopulate": false,
      "autoPopulatePrefix": "",
      "widgetPane": {
        "gridSize": 128.0,
        "showGrid": true,
        "hgap": 16.0,
        "vgap": 16.0,
        "titleType": 0,
        "tiles": {}
      }
    },
    {
      "title": "Test",
      "autoPopulate": false,
      "autoPopulatePrefix": "",
      "widgetPane": {
        "gridSize": 128.0,
        "showGrid": true,
        "hgap": 16.0,
        "vgap": 16.0,
        "titleType": 0,
        "tiles": {
          "3,0": {
            "size": [
              3,
              1
            ],
            "content": {
              "_type": "Basic FMS Info",
              "_source0": "network_table:///FMSInfo",
              "_title": "FMSInfo",
              "_glyph": 148,
              "_showGlyph": false
            }
          },
          "2,0": {
            "size": [
              1,
              3
            ],
            "content": {
              "_type": "List Layout",
              "_title": "Pneumatics",
              "_glyph": 149,
              "_showGlyph": false,
              "Layout/Label position": "BOTTOM",
              "_children": [
                {
                  "_type": "Boolean Box",
                  "_source0": "network_table:///SmartDashboard/Intake Solenoid",
                  "_title": "Intake",
                  "_glyph": 148,
                  "_showGlyph": false,
                  "Colors/Color when true": "#7CFC00FF",
                  "Colors/Color when false": "#8B0000FF"
                },
                {
                  "_type": "Boolean Box",
                  "_source0": "network_table:///SmartDashboard/Clamp Solenoid",
                  "_title": "Clamp",
                  "_glyph": 148,
                  "_showGlyph": false,
                  "Colors/Color when true": "#7CFC00FF",
                  "Colors/Color when false": "#8B0000FF"
                }
              ]
            }
          },
          "1,0": {
            "size": [
              1,
              3
            ],
            "content": {
              "_type": "List Layout",
              "_title": "Motors",
              "_glyph": 149,
              "_showGlyph": false,
              "Layout/Label position": "BOTTOM",
              "_children": [
                {
                  "_type": "Number Bar",
                  "_source0": "network_table:///SmartDashboard/Intake Motor",
                  "_title": "Intake",
                  "_glyph": 148,
                  "_showGlyph": false,
                  "Range/Min": -1.0,
                  "Range/Max": 1.0,
                  "Range/Center": 0.0,
                  "Visuals/Num tick marks": 5,
                  "Visuals/Show text": true,
                  "Visuals/Orientation": "HORIZONTAL"
                }
              ]
            }
          },
          "8,0": {
            "size": [
              1,
              3
            ],
            "content": {
              "_type": "Grid Layout",
              "_title": "Arm Info",
              "_glyph": 149,
              "_showGlyph": false,
              "Layout/Number of columns": 3,
              "Layout/Number of rows": 3,
              "Layout/Label position": "BOTTOM",
              "_children": {}
            }
          },
          "6,0": {
            "size": [
              2,
              3
            ],
            "content": {
              "_type": "List Layout",
              "_title": "Arm Preset",
              "_glyph": 149,
              "_showGlyph": false,
              "Layout/Label position": "BOTTOM",
              "_children": [
                {
                  "_type": "ComboBox Chooser",
                  "_source0": "network_table:///SmartDashboard/Manual Arm",
                  "_title": "Manual Arm Enabled",
                  "_glyph": 148,
                  "_showGlyph": false
                },
                {
                  "_type": "ComboBox Chooser",
                  "_source0": "network_table:///SmartDashboard/Arm Preset",
                  "_title": "Manual Arm Preset",
                  "_glyph": 148,
                  "_showGlyph": false
                }
              ]
            }
          },
          "3,1": {
            "size": [
              3,
              2
            ],
            "content": {
              "_type": "Differential Drivebase",
              "_source0": "network_table:///SmartDashboard/jMoneyDrive",
              "_title": "jMoneyDrive",
              "_glyph": 148,
              "_showGlyph": false,
              "Wheels/Number of wheels": 4,
              "Wheels/Wheel diameter": 80.0,
              "Visuals/Show velocity vectors": true
            }
          }
        }
      }
    },
    {
      "title": "Setup",
      "autoPopulate": false,
      "autoPopulatePrefix": "",
      "widgetPane": {
        "gridSize": 128.0,
        "showGrid": true,
        "hgap": 16.0,
        "vgap": 16.0,
        "titleType": 0,
        "tiles": {
          "3,0": {
            "size": [
              4,
              1
            ],
            "content": {
              "_type": "Basic FMS Info",
              "_source0": "network_table:///FMSInfo",
              "_title": "FMSInfo",
              "_glyph": 148,
              "_showGlyph": false
            }
          }
        }
      }
    }
  ],
  "windowGeometry": {
    "x": 243.0,
    "y": 121.0,
    "width": 1460.0,
    "height": 875.0
  }
}